pixel_classifier_torch-0.2.data/data/requirements.txt
segmentation/__init__.py
segmentation/dataset.py
segmentation/model.py
segmentation/modules.py
segmentation/network.py
segmentation/optimizer.py
segmentation/settings.py
segmentation/util.py
segmentation/gui/__init__.py
segmentation/gui/gui.py
segmentation/gui/xml_util.py
segmentation/postprocessing/__init__.py
segmentation/postprocessing/baseline_extraction.py
segmentation/postprocessing/baseline_postprocess_by_borders.py
segmentation/postprocessing/data_classes.py
segmentation/postprocessing/layout_analysis.py
segmentation/postprocessing/marginialia_detection.py
segmentation/postprocessing/simplify_line.py
segmentation/postprocessing/text_border_estimation.py
segmentation/postprocessing/util.py
segmentation/preprocessing/__init__.py
segmentation/preprocessing/basic_binarizer.py
segmentation/preprocessing/ocrupus.py
segmentation/preprocessing/util.py
segmentation/scripts/__init__.py
segmentation/scripts/eval.py
segmentation/scripts/image_map.py
segmentation/scripts/ods_runner.py
segmentation/scripts/predict.py
segmentation/scripts/train.py
pixel_classifier_torch-0.2.dist-info/LICENSE.md
pixel_classifier_torch-0.2.dist-info/METADATA
pixel_classifier_torch-0.2.dist-info/WHEEL
pixel_classifier_torch-0.2.dist-info/entry_points.txt
pixel_classifier_torch-0.2.dist-info/top_level.txt
pixel_classifier_torch-0.2.dist-info/RECORD
