Metadata-Version: 2.1
Name: pixel-classifier-torch
Version: 0.2
Summary: UNKNOWN
Home-page: https://github.com/Gawajn/segmentation-pytorch
Author: Alexander Hartelt
Author-email: alexander.hartelt@informatik.uni-wuerzburg.de
License: UNKNOWN
Keywords: OCR,page segmentation,pixel classifier
Platform: UNKNOWN
Classifier: Programming Language :: Python :: 3
Classifier: License :: OSI Approved :: GNU General Public License v3 or later (GPLv3+)
Classifier: License :: OSI Approved :: Apache Software License
Classifier: Intended Audience :: Science/Research
Classifier: Topic :: Scientific/Engineering :: Image Recognition
Requires-Dist: segmentation-models-pytorch
Requires-Dist: torch
Requires-Dist: PageXML-to-Mask-converter
Requires-Dist: torchvision
Requires-Dist: pillow (~=6.2.1)
Requires-Dist: numpy (~=1.17.4)
Requires-Dist: ttach
Requires-Dist: setuptools (~=41.6.0)
Requires-Dist: matplotlib (~=3.1.1)
Requires-Dist: pandas (~=0.25.3)
Requires-Dist: seaborn (~=0.9.0)
Requires-Dist: tqdm (~=4.38.0)
Requires-Dist: albumentations (~=0.4.2)
Requires-Dist: scikit-image (~=0.16.2)
Requires-Dist: opencv-python
Requires-Dist: sklearn (~=0.0)
Requires-Dist: ezodf (~=0.3.2)
Requires-Dist: lxml
Requires-Dist: shapely (~=1.7.0)
Requires-Dist: future (~=0.18.2)
Requires-Dist: scikit-learn (~=0.21.3)
Requires-Dist: dataclasses
Requires-Dist: dataclasses-json
Requires-Dist: scikit-learn
Requires-Dist: scipy (~=1.3.2)
